{
  "auth": {
    "natourd60c9a65": {
      "dependsOn": [
        {
          "category": "function",
          "resourceName": "natourd60c9a65PostConfirmation",
          "triggerProvider": "Cognito",
          "attributes": [
            "Arn",
            "Name"
          ]
        }
      ]
    }
  },
  "function": {
    "natourd60c9a65PostConfirmation": {
      "build": true,
      "providerPlugin": "awscloudformation",
      "service": "Lambda"
    }
  },
  "storage": {
    "s3natour": {
      "service": "S3",
      "providerPlugin": "awscloudformation",
      "dependsOn": []
    }
  }
}